{
    "status": true,
    "timestamp": 1730394380410,
    "data": {
        "id": 207108528,
        "name": "Mango button front midi dress in black",
        "description": "<a href=\"/women/dresses/cat/?cid=8799\"><strong>Dresses</strong></a> by <a href=\"/women/a-to-z-of-brands/mango/cat/?cid=8264\"><strong>Mango</strong></a><br><ul><li>Too good to only wear once</li><li>Plain design</li><li>V-neck</li><li>Button placket</li><li>Short sleeves</li><li>Regular fit</li></ul>",
        "localisedData": [
            {
                "locale": "en-GB",
                "title": "Mango button front midi dress in black",
                "pdpUrl": "https://www.asos.com/mango/mango-button-front-midi-dress-in-black/prd/207108528"
            },
            {
                "locale": "en-US",
                "title": "Mango button front midi dress in black",
                "pdpUrl": "https://www.asos.com/us/mango/mango-button-front-midi-dress-in-black/prd/207108528"
            },
            {
                "locale": "de-DE",
                "title": "Mango \u2013 Midikleid in Schwarz mit Kn\u00f6pfen vorne",
                "pdpUrl": "https://www.asos.com/de/mango/mango-midikleid-in-schwarz-mit-knopfen-vorne/prd/207108528"
            },
            {
                "locale": "fr-FR",
                "title": "Mango - Robe mi-longue boutonn\u00e9e devant - Noir",
                "pdpUrl": "https://www.asos.com/fr/mango/mango-robe-mi-longue-boutonnee-devant-noir/prd/207108528"
            },
            {
                "locale": "sv-SE",
                "title": "Mango \u2013 Svart midikl\u00e4nning med knappar framtill",
                "pdpUrl": "https://www.asos.com/se/mango/mango-svart-midiklanning-med-knappar-framtill/prd/207108528"
            },
            {
                "locale": "da-DK",
                "title": "Mango - Sort midikjole med knapper",
                "pdpUrl": "https://www.asos.com/dk/mango/mango-sort-midikjole-med-knapper/prd/207108528"
            },
            {
                "locale": "it-IT",
                "title": "Mango - Vestito midi nero con bottoni sul davanti",
                "pdpUrl": "https://www.asos.com/it/mango/mango-vestito-midi-nero-con-bottoni-sul-davanti/prd/207108528"
            },
            {
                "locale": "pl-PL",
                "title": "Mango \u2013 Czarna sukienka midi, zapinana na guziki z przodu",
                "pdpUrl": "https://www.asos.com/pl/mango/mango-czarna-sukienka-midi-zapinana-na-guziki-z-przodu/prd/207108528"
            },
            {
                "locale": "es-ES",
                "title": "Vestido midi negro con botones delanteros de Mango",
                "pdpUrl": "https://www.asos.com/es/mango/vestido-midi-negro-con-botones-delanteros-de-mango/prd/207108528"
            },
            {
                "locale": "nl-NL",
                "title": "Mango - Midi jurk met knoopsluiting aan de voorkant in zwart",
                "pdpUrl": "https://www.asos.com/nl/mango/mango-midi-jurk-met-knoopsluiting-aan-de-voorkant-in-zwart/prd/207108528"
            }
        ],
        "gender": "Women",
        "productCode": "137725311",
        "pdpLayout": "Core",
        "brand": {
            "id": 12117,
            "name": "Mango",
            "description": "The designers behind Barcelona-born <a href=\"/women/a-to-z-of-brands/mango/cat/?cid=8264\"><strong>Mango</strong></a> know that pairing timeless style with minimalist design is a winning formula. We\u2019ve handpicked our fave pieces from its dreamy collections \u2013 think dresses, denim and jackets to keep you on top of your game, plus tailored separates to dress up or down. Its shoes and pretty accessories are on our wishlist, too."
        },
        "sizeGuide": "https://www.asos.com/web/pages/size-guides/index.html?sizeSchema=US&data=https://www.asos.com/api/sizing/sizeapi/v1/SizeGuide/8798%3flanguage%3den-GB",
        "isNoSize": false,
        "isOneSize": false,
        "hasVariantsWithProp65Risk": true,
        "variants": [
            {
                "id": 207108558,
                "name": "Mango button front midi dress in black",
                "sizeId": 410901,
                "brandSize": "XS",
                "displaySizeText": "XS - US 2",
                "sizeOrder": 2,
                "sku": "137725431",
                "isAvailable": true,
                "colourWayId": 207108545,
                "colour": "BLACK",
                "isPrimary": true,
                "isProp65Risk": true,
                "ean": "8447144584317"
            },
            {
                "id": 207108559,
                "name": "Mango button front midi dress in black",
                "sizeId": 410898,
                "brandSize": "S",
                "displaySizeText": "S - US 4",
                "sizeOrder": 3,
                "sku": "137725432",
                "isAvailable": true,
                "colourWayId": 207108545,
                "colour": "BLACK",
                "isPrimary": true,
                "isProp65Risk": true,
                "ean": "8447144584324"
            },
            {
                "id": 207108556,
                "name": "Mango button front midi dress in black",
                "sizeId": 410899,
                "brandSize": "M",
                "displaySizeText": "M - US 6",
                "sizeOrder": 4,
                "sku": "137725433",
                "isAvailable": true,
                "colourWayId": 207108545,
                "colour": "BLACK",
                "isPrimary": true,
                "isProp65Risk": true,
                "ean": "8447144584331"
            },
            {
                "id": 207108557,
                "name": "Mango button front midi dress in black",
                "sizeId": 410902,
                "brandSize": "L",
                "displaySizeText": "L - US 8",
                "sizeOrder": 5,
                "sku": "137725434",
                "isAvailable": true,
                "colourWayId": 207108545,
                "colour": "BLACK",
                "isPrimary": true,
                "isProp65Risk": true,
                "ean": "8447144584348"
            },
            {
                "id": 207108560,
                "name": "Mango button front midi dress in black",
                "sizeId": 410900,
                "brandSize": "XL",
                "displaySizeText": "XL - US 10",
                "sizeOrder": 6,
                "sku": "137725435",
                "isAvailable": true,
                "colourWayId": 207108545,
                "colour": "BLACK",
                "isPrimary": true,
                "isProp65Risk": true,
                "ean": "8447144584355"
            }
        ],
        "media": {
            "images": [
                {
                    "url": "images.asos-media.com/products/mango-button-front-midi-dress-in-black/207108528-1-black",
                    "type": "Standard1",
                    "colourWayId": 207108545,
                    "colour": "BLACK",
                    "isPrimary": true
                },
                {
                    "url": "images.asos-media.com/products/mango-button-front-midi-dress-in-black/207108528-2",
                    "type": "Standard2",
                    "colourWayId": null,
                    "colour": "",
                    "isPrimary": false
                },
                {
                    "url": "images.asos-media.com/products/mango-button-front-midi-dress-in-black/207108528-3",
                    "type": "Standard3",
                    "colourWayId": null,
                    "colour": "",
                    "isPrimary": false
                },
                {
                    "url": "images.asos-media.com/products/mango-button-front-midi-dress-in-black/207108528-4",
                    "type": "Standard4",
                    "colourWayId": null,
                    "colour": "",
                    "isPrimary": false
                }
            ],
            "catwalk": [
                {
                    "assetId": "207108528-catwalk",
                    "url": "www.asos-video.com/video/upload/q_auto/t_legacy_product_video/207108528-catwalk",
                    "colourWayId": 207108545
                }
            ],
            "spinset": [],
            "swatchSprite": []
        },
        "badges": [],
        "info": {
            "aboutMe": "Linen-mix fabric: soft and lightweight<br><br>Main: 85% Viscose, 15% Linen.",
            "sizeAndFit": "Model's height: 174cm / 5' 8''<br/>Model is wearing: S - US 4",
            "careInfo": "Machine wash according to instructions on care label"
        },
        "associatedGroups": {
            "looks": [
                {
                    "id": 207410274,
                    "type": "heroLook",
                    "url": "https://api.asos.com/product/catalogue/v4/productlooks?lookIds=207410274&store=ROW"
                }
            ]
        },
        "shippingRestriction": {
            "includedCountryCodes": [
                "AD",
                "AE",
                "AG",
                "AI",
                "AL",
                "AO",
                "AR",
                "AS",
                "AT",
                "AW",
                "AX",
                "AZ",
                "BA",
                "BB",
                "BD",
                "BE",
                "BF",
                "BG",
                "BH",
                "BI",
                "BJ",
                "BL",
                "BM",
                "BN",
                "BO",
                "BQ",
                "BR",
                "BS",
                "BT",
                "BW",
                "BZ",
                "CA",
                "CD",
                "CF",
                "CG",
                "CH",
                "CI",
                "CK",
                "CL",
                "CM",
                "CN",
                "CO",
                "CR",
                "CV",
                "CW",
                "CY",
                "CZ",
                "DE",
                "DJ",
                "DK",
                "DM",
                "DZ",
                "EC",
                "EE",
                "EG",
                "EH",
                "ER",
                "ES",
                "ET",
                "FI",
                "FJ",
                "FK",
                "FM",
                "FO",
                "FR",
                "GA",
                "GB",
                "GD",
                "GF",
                "GH",
                "GI",
                "GL",
                "GM",
                "GN",
                "GP",
                "GQ",
                "GR",
                "GT",
                "GU",
                "GW",
                "GY",
                "HN",
                "HR",
                "HU",
                "IE",
                "IN",
                "IQ",
                "IS",
                "IT",
                "JM",
                "JO",
                "JP",
                "KH",
                "KI",
                "KN",
                "KR",
                "KW",
                "KY",
                "LA",
                "LC",
                "LI",
                "LK",
                "LR",
                "LS",
                "LT",
                "LU",
                "LV",
                "MA",
                "MC",
                "MD",
                "ME",
                "MF",
                "MG",
                "MH",
                "MK",
                "ML",
                "MN",
                "MO",
                "MP",
                "MQ",
                "MR",
                "MS",
                "MT",
                "MU",
                "MV",
                "MW",
                "MX",
                "MZ",
                "NA",
                "NC",
                "NE",
                "NG",
                "NI",
                "NL",
                "NO",
                "NP",
                "NR",
                "NU",
                "NZ",
                "OM",
                "PA",
                "PE",
                "PF",
                "PG",
                "PK",
                "PL",
                "PM",
                "PN",
                "PR",
                "PT",
                "PW",
                "PY",
                "QA",
                "RE",
                "RO",
                "RS",
                "RW",
                "SA",
                "SB",
                "SC",
                "SE",
                "SH",
                "SI",
                "SK",
                "SL",
                "SN",
                "SR",
                "ST",
                "SV",
                "SX",
                "SZ",
                "TC",
                "TD",
                "TG",
                "TH",
                "TK",
                "TN",
                "TO",
                "TT",
                "TV",
                "TZ",
                "UG",
                "US",
                "UY",
                "VC",
                "VG",
                "VI",
                "VN",
                "VU",
                "WF",
                "WS",
                "YT",
                "ZA",
                "ZM",
                "ZW"
            ],
            "excludedCountryCodes": [
                "AU",
                "HK",
                "ID",
                "PH",
                "RU",
                "IL",
                "TW",
                "SG",
                "MY"
            ]
        },
        "rating": null,
        "productType": {
            "id": 8416,
            "name": "Dresses"
        },
        "plpIds": [
            {
                "id": 5235,
                "type": "Standard"
            },
            {
                "id": 7046,
                "type": "Standard"
            },
            {
                "id": 8799,
                "type": "SEO"
            },
            {
                "id": 8834,
                "type": "Standard"
            },
            {
                "id": 12899,
                "type": "Standard"
            },
            {
                "id": 13053,
                "type": "Standard"
            },
            {
                "id": 13489,
                "type": "Standard"
            },
            {
                "id": 15623,
                "type": "Standard"
            },
            {
                "id": 15626,
                "type": "Standard"
            },
            {
                "id": 15944,
                "type": "Standard"
            },
            {
                "id": 15945,
                "type": "Standard"
            },
            {
                "id": 19680,
                "type": "Standard"
            },
            {
                "id": 20037,
                "type": "Standard"
            },
            {
                "id": 20493,
                "type": "Standard"
            },
            {
                "id": 21252,
                "type": "Brand"
            },
            {
                "id": 28023,
                "type": "Standard"
            },
            {
                "id": 28254,
                "type": "Standard"
            },
            {
                "id": 50005,
                "type": "Standard"
            },
            {
                "id": 50046,
                "type": "Standard"
            },
            {
                "id": 50047,
                "type": "Standard"
            },
            {
                "id": 50053,
                "type": "Standard"
            },
            {
                "id": 50711,
                "type": "Standard"
            },
            {
                "id": 50712,
                "type": "Standard"
            },
            {
                "id": 50713,
                "type": "Standard"
            },
            {
                "id": 50715,
                "type": "Standard"
            },
            {
                "id": 50717,
                "type": "Standard"
            },
            {
                "id": 50718,
                "type": "Standard"
            },
            {
                "id": 51339,
                "type": "Standard"
            },
            {
                "id": 51390,
                "type": "Standard"
            },
            {
                "id": 52057,
                "type": "Standard"
            },
            {
                "id": 52078,
                "type": "Standard"
            },
            {
                "id": 52079,
                "type": "Standard"
            }
        ],
        "brandType": null,
        "hairType": null,
        "skinType": null,
        "sellingTags": [],
        "isDiscontinued": false
    }
}